get_mp3_from_url/__init__.py
get_mp3_from_url/main.py
get_mp3_from_url/song_downloader.py
test/__init__.py
test/test_main.py
test/test_song_downloader.py
get_mp3_from_url-0.0.0.dist-info/LICENSE
get_mp3_from_url-0.0.0.dist-info/METADATA
get_mp3_from_url-0.0.0.dist-info/WHEEL
get_mp3_from_url-0.0.0.dist-info/entry_points.txt
get_mp3_from_url-0.0.0.dist-info/top_level.txt
get_mp3_from_url-0.0.0.dist-info/RECORD
