Metadata-Version: 2.1
Name: get-mp3-from-url
Version: 0.0.0
Summary: A tool to download mp3 files from url
Home-page: https://github.com/renn0xtek9/get_mp3_from_url
Author: Maxime Haselbauer
Author-email: maxime.haselbauer@googlemail.com
License: MIT
Keywords: keywords
Platform: UNKNOWN
Classifier: Programming Language :: Python :: 3
Classifier: License :: OSI Approved :: MIT License
Classifier: Operating System :: OS Independent
License-File: LICENSE
Requires-Dist: ffmpeg
Requires-Dist: yt-dlp
